odoo/addons/hr_expense_advance_clearing/README.rst
odoo/addons/hr_expense_advance_clearing/__init__.py
odoo/addons/hr_expense_advance_clearing/__manifest__.py
odoo/addons/hr_expense_advance_clearing/data/advance_product.xml
odoo/addons/hr_expense_advance_clearing/i18n/hr_expense_advance_clearing.pot
odoo/addons/hr_expense_advance_clearing/models/__init__.py
odoo/addons/hr_expense_advance_clearing/models/hr_expense.py
odoo/addons/hr_expense_advance_clearing/models/hr_expense_sheet.py
odoo/addons/hr_expense_advance_clearing/readme/CONFIGURE.rst
odoo/addons/hr_expense_advance_clearing/readme/CONTRIBUTORS.rst
odoo/addons/hr_expense_advance_clearing/readme/DESCRIPTION.rst
odoo/addons/hr_expense_advance_clearing/readme/INSTALL.rst
odoo/addons/hr_expense_advance_clearing/readme/USAGE.rst
odoo/addons/hr_expense_advance_clearing/static/description/icon.png
odoo/addons/hr_expense_advance_clearing/static/description/index.html
odoo/addons/hr_expense_advance_clearing/tests/__init__.py
odoo/addons/hr_expense_advance_clearing/tests/test_hr_expense_advance_clearing.py
odoo/addons/hr_expense_advance_clearing/views/hr_expense_views.xml
odoo/addons/hr_expense_advance_clearing/wizard/__init__.py
odoo/addons/hr_expense_advance_clearing/wizard/hr_expense_sheet_register_payment.py
odoo13_addon_hr_expense_advance_clearing-13.0.1.2.0.dist-info/METADATA
odoo13_addon_hr_expense_advance_clearing-13.0.1.2.0.dist-info/WHEEL
odoo13_addon_hr_expense_advance_clearing-13.0.1.2.0.dist-info/top_level.txt
odoo13_addon_hr_expense_advance_clearing-13.0.1.2.0.dist-info/RECORD
